conoha_client/__init__.py
conoha_client/_shared/__init__.py
conoha_client/_shared/add_vm/__init__.py
conoha_client/_shared/add_vm/domain/__init__.py
conoha_client/_shared/add_vm/domain/domain.py
conoha_client/_shared/add_vm/domain/errors.py
conoha_client/_shared/add_vm/domain/test_domain.py
conoha_client/_shared/add_vm/options.py
conoha_client/_shared/add_vm/repo.py
conoha_client/_shared/add_vm/test_repo.py
conoha_client/_shared/renforced_vm/__init__.py
conoha_client/_shared/renforced_vm/cli.py
conoha_client/_shared/renforced_vm/domain.py
conoha_client/_shared/renforced_vm/query.py
conoha_client/_shared/snapshot/__init__.py
conoha_client/_shared/snapshot/repo.py
conoha_client/_shared/ssh_template.py
conoha_client/cli.py
conoha_client/features/__init__.py
conoha_client/features/_shared/__init__.py
conoha_client/features/_shared/command_option/__init__.py
conoha_client/features/_shared/command_option/build_vm_options.py
conoha_client/features/_shared/command_option/default_callback.py
conoha_client/features/_shared/command_option/each_args.py
conoha_client/features/_shared/command_option/test_each_args.py
conoha_client/features/_shared/conftest.py
conoha_client/features/_shared/endpoints/__init__.py
conoha_client/features/_shared/endpoints/endpoints.py
conoha_client/features/_shared/endpoints/environments.py
conoha_client/features/_shared/endpoints/test_endpoints.py
conoha_client/features/_shared/endpoints/test_env.py
conoha_client/features/_shared/endpoints/token.py
conoha_client/features/_shared/model_list/__init__.py
conoha_client/features/_shared/model_list/domain.py
conoha_client/features/_shared/model_list/test_domain.py
conoha_client/features/_shared/prompt.py
conoha_client/features/_shared/util.py
conoha_client/features/_shared/view/__init__.py
conoha_client/features/_shared/view/domain.py
conoha_client/features/_shared/view/test_domain.py
conoha_client/features/billing/__init__.py
conoha_client/features/billing/cli.py
conoha_client-0.4.3.dist-info/METADATA
conoha_client-0.4.3.dist-info/WHEEL
conoha_client-0.4.3.dist-info/entry_points.txt
conoha_client-0.4.3.dist-info/RECORD
