Metadata-Version: 2.1
Name: conoha-client
Version: 0.4.3
Summary: ConoHa VPS用CLI (2023.11)
Home-page: https://github.com/shogogoto/conoha-client
Author: Shogo Goto
Author-email: gotoadmn0605@gmail.com
Requires-Python: >=3.10,<4.0
Classifier: Programming Language :: Python :: 3
Classifier: Programming Language :: Python :: 3.10
Classifier: Programming Language :: Python :: 3.11
Requires-Dist: click (>=8.1.7,<9.0.0)
Requires-Dist: click-shell (>=2.1,<3.0)
Requires-Dist: flatten-dict (>=0.4.2,<0.5.0)
Requires-Dist: makefun (>=1.15.1,<2.0.0)
Requires-Dist: pydantic (>=2.4.0,<3.0.0)
Requires-Dist: python-dateutil (>=2.8.2,<3.0.0)
Requires-Dist: python-openstackclient (>=6.2.0,<7.0.0)
Requires-Dist: tabulate (>=0.9.0,<0.10.0)
Project-URL: Repository, https://github.com/shogogoto/conoha-client
